scil/Preprocessing.py
scil/__init__.py
scil/anew.pickle
scil/emotive_words.pickle
scil/scil.py
scil/topic extraction.py
scil/services/__init__.py
scil/services/_agreement.py
scil/services/_argumentDiversity.py
scil/services/_disagreement.py
scil/services/_emotiveLanguageUse.py
scil/services/_involvement.py
scil/services/_networkCentrality.py
scil/services/_preprocessing.py
scil/services/_sociability.py
scil/services/_socialPositioning.py
scil/services/_socialRoles.py
scil/services/_taskControl.py
scil/services/_taskFocus.py
scil/services/_tensionFocus.py
scil/services/_topicControl.py
scil/services/_topicalPositioning.py
scil/stanford-postagger-full-2015-04-20/LICENSE.txt
scil/stanford-postagger-full-2015-04-20/README.txt
scil/stanford-postagger-full-2015-04-20/TaggerDemo.java
scil/stanford-postagger-full-2015-04-20/TaggerDemo2.java
scil/stanford-postagger-full-2015-04-20/build.xml
scil/stanford-postagger-full-2015-04-20/sample-input.txt
scil/stanford-postagger-full-2015-04-20/sample-output.txt
scil/stanford-postagger-full-2015-04-20/stanford-postagger-gui.bat
scil/stanford-postagger-full-2015-04-20/stanford-postagger-gui.sh
scil/stanford-postagger-full-2015-04-20/stanford-postagger.bat
scil/stanford-postagger-full-2015-04-20/stanford-postagger.jar
scil/stanford-postagger-full-2015-04-20/stanford-postagger.sh
scil/stanford-postagger-full-2015-04-20/data/enclitic-inflections.data
scil/stanford-postagger-full-2015-04-20/models/README-Models.txt
scil/stanford-postagger-full-2015-04-20/models/english-bidirectional-distsim.tagger
scil/stanford-postagger-full-2015-04-20/models/english-bidirectional-distsim.tagger.props
scil/stanford-postagger-full-2015-04-20/models/english-caseless-left3words-distsim.tagger
scil/stanford-postagger-full-2015-04-20/models/english-caseless-left3words-distsim.tagger.props
scil/stanford-postagger-full-2015-04-20/models/english-left3words-distsim.tagger
scil/stanford-postagger-full-2015-04-20/models/english-left3words-distsim.tagger.props
pySCIL-0.0.12.dist-info/LICENSE
pySCIL-0.0.12.dist-info/METADATA
pySCIL-0.0.12.dist-info/WHEEL
pySCIL-0.0.12.dist-info/top_level.txt
pySCIL-0.0.12.dist-info/RECORD
