Metadata-Version: 2.1
Name: pySCIL
Version: 0.0.12
Summary: A sociolinguistics package for NLP research.
Home-page: https://github.com/Malorn44/pySCIL
Author: Mara Schwartz, Esteban Castillo Juarez, Ivan Leon
Author-email: maraschwartz44@gmail.com, castie2@rpi.edu, leoni@rpi.edu
Project-URL: Documentation, https://github.com/Malorn44/pySCIL
Project-URL: Source Code, https://github.com/Malorn44/pySCIL
Classifier: Programming Language :: Python :: 3
Classifier: License :: OSI Approved :: MIT License
Classifier: Operating System :: OS Independent
Requires-Python: >=3.6
License-File: LICENSE
